MANIFEST.in
README.rst
setup.py
docs/HISTORY.txt
docs/LICENSE.GPL
docs/LICENSE.txt
ftw/__init__.py
ftw.oidcauth.egg-info/PKG-INFO
ftw.oidcauth.egg-info/SOURCES.txt
ftw.oidcauth.egg-info/dependency_links.txt
ftw.oidcauth.egg-info/entry_points.txt
ftw.oidcauth.egg-info/namespace_packages.txt
ftw.oidcauth.egg-info/not-zip-safe
ftw.oidcauth.egg-info/requires.txt
ftw.oidcauth.egg-info/top_level.txt
ftw/oidcauth/__init__.py
ftw/oidcauth/configure.zcml
ftw/oidcauth/errors.py
ftw/oidcauth/helper.py
ftw/oidcauth/plugin.py
ftw/oidcauth/testing.py
ftw/oidcauth/browser/__init__.py
ftw/oidcauth/browser/configure.zcml
ftw/oidcauth/browser/oidc.py
ftw/oidcauth/browser/oidc_tools.py
ftw/oidcauth/tests/__init__.py
ftw/oidcauth/tests/test_errors_inherit_from_base.py
ftw/oidcauth/tests/test_oidc_client_authentication.py
ftw/oidcauth/tests/test_oidc_view.py
ftw/oidcauth/tests/test_user_handler.py
ftw/oidcauth/www/addPlugin.zpt
ftw/oidcauth/www/config.zpt
ftw/oidcauth/www/manage_users.zpt