Metadata-Version: 2.1
Name: ftw.oidcauth
Version: 1.0.1
Summary: A PAS plugin for authentication of users in Plone using OIDC.
Home-page: https://github.com/4teamwork/ftw.oidcauth
Author: 4teamwork AG
Author-email: info@4teamwork.ch
License: GPL
Platform: UNKNOWN
Classifier: Framework :: Plone
Classifier: Framework :: Plone :: 4.3
Classifier: Framework :: Plone :: 5.1
Classifier: Programming Language :: Python
Classifier: Topic :: Software Development :: Libraries :: Python Modules
Provides-Extra: tests
